revolve2/ci_group/__init__.py
revolve2/ci_group/modular_robots_v2.py
revolve2/ci_group/terrains.py
revolve2/ci_group/simulation_parameters.py
revolve2/ci_group/fitness_functions.py
revolve2/ci_group/py.typed
revolve2/ci_group/planar_robot_representation.py
revolve2/ci_group/modular_robots_v1.py
revolve2/ci_group/morphological_measures.py
revolve2/ci_group/morphological_novelty_metric/__init__.py
revolve2/ci_group/morphological_novelty_metric/_coordinate_operations.py
revolve2/ci_group/morphological_novelty_metric/calculate_novelty.pyi
revolve2/ci_group/morphological_novelty_metric/calculate_novelty.cpython-311-x86_64-linux-musl.so
revolve2/ci_group/morphological_novelty_metric/_build_cmodule.py
revolve2/ci_group/morphological_novelty_metric/calculate_novelty.cpython-310-x86_64-linux-gnu.so
revolve2/ci_group/morphological_novelty_metric/_calculate_novelty.pyx
revolve2/ci_group/morphological_novelty_metric/_morphological_novelty_metric.py
revolve2/ci_group/interactive_objects/__init__.py
revolve2/ci_group/interactive_objects/_ball.py
revolve2/ci_group/genotypes/__init__.py
revolve2/ci_group/genotypes/cppnwin/_random_multineat_genotype.py
revolve2/ci_group/genotypes/cppnwin/__init__.py
revolve2/ci_group/genotypes/cppnwin/_multineat_genotype_pickle_wrapper.py
revolve2/ci_group/genotypes/cppnwin/_multineat_rng_from_random.py
revolve2/ci_group/genotypes/cppnwin/modular_robot/_brain_genotype_cpg.py
revolve2/ci_group/genotypes/cppnwin/modular_robot/_multineat_params.py
revolve2/ci_group/genotypes/cppnwin/modular_robot/__init__.py
revolve2/ci_group/genotypes/cppnwin/modular_robot/_brain_cpg_network_neighbor.py
revolve2/ci_group/genotypes/cppnwin/modular_robot/_brain_genotype_cpg_orm.py
revolve2/ci_group/genotypes/cppnwin/modular_robot/v2/__init__.py
revolve2/ci_group/genotypes/cppnwin/modular_robot/v2/_body_genotype_v2.py
revolve2/ci_group/genotypes/cppnwin/modular_robot/v2/_body_develop.py
revolve2_ci_group-1.2.1.dist-info/WHEEL
revolve2_ci_group-1.2.1.dist-info/RECORD
revolve2_ci_group-1.2.1.dist-info/METADATA
