Metadata-Version: 2.1
Name: revolve2-ci-group
Version: 1.2.1
Summary: Revolve2: Computational Intelligence Group experimentation tools and standards.
Home-page: https://github.com/ci-group/revolve2
Author: Aart Stuurman
Author-email: aartstuurman@hotmail.com
Requires-Python: >=3.10,<3.12
Classifier: Development Status :: 5 - Production/Stable
Classifier: Intended Audience :: Science/Research
Classifier: License :: OSI Approved :: GNU Lesser General Public License v3 (LGPLv3)
Classifier: Operating System :: OS Independent
Classifier: Programming Language :: Python :: 3
Classifier: Programming Language :: Python :: 3.10
Classifier: Programming Language :: Python :: 3.11
Classifier: Topic :: Scientific/Engineering
Classifier: Typing :: Typed
Provides-Extra: dev
Requires-Dist: Cython (>=3.0.4,<4.0.0)
Requires-Dist: multineat (>=0.12,<0.13)
Requires-Dist: noise (>=1.2.2,<2.0.0)
Requires-Dist: numpy (>=1.21.2,<2.0.0)
Requires-Dist: opencv-contrib-python (>=4.9.0.80,<5.0.0.0)
Requires-Dist: opencv-python (>=4.9.0.80,<5.0.0.0)
Requires-Dist: revolve2-modular-robot-simulation (==1.2.1)
Requires-Dist: setuptools (>=70.0.0,<71.0.0)
Requires-Dist: sqlalchemy (>=2.0.0,<3.0.0)
Project-URL: Repository, https://github.com/ci-group/revolve2
